epok_toolkit/__init__.py
epok_toolkit/apps.py
epok_toolkit/default_settings.py
epok_toolkit/django/__init__.py
epok_toolkit/django/cache.py
epok_toolkit/django/fields.py
epok_toolkit/django/manager.py
epok_toolkit/django/models.py
epok_toolkit/django/response.py
epok_toolkit/django/viewsets.py
epok_toolkit/django/utils/__init__.py
epok_toolkit/django/utils/magic_link.py
epok_toolkit/email/__init__.py
epok_toolkit/email/email_async.py
epok_toolkit/email/engine.py
epok_toolkit/email/templates.py
epok_toolkit/messaging/__init__.py
epok_toolkit/messaging/whatsapp.py
epok_toolkit/messaging/whatsapp_instanced.py
epok_toolkit/pdf/__init__.py
epok_toolkit/pdf/ticket_pdf.py
epok_toolkit/pdf/fuentes/Kollektif-Bold.ttf
epok_toolkit/pdf/fuentes/Kollektif-BoldItalic.ttf
epok_toolkit/pdf/fuentes/Kollektif-Italic.ttf
epok_toolkit/pdf/fuentes/Kollektif.ttf
epok_toolkit/pdf/plantillas/Ticket_congrats.png
epok_toolkit/pdf/plantillas/Ticket_congrats2.png
epok_toolkit-1.12.8.dist-info/licenses/LICENSE
epok_toolkit-1.12.8.dist-info/METADATA
epok_toolkit-1.12.8.dist-info/WHEEL
epok_toolkit-1.12.8.dist-info/top_level.txt
epok_toolkit-1.12.8.dist-info/RECORD
