Metadata-Version: 2.4
Name: epok-toolkit
Version: 1.12.8
Summary: Una herramienta para la gestión de tareas y procesos en Django con Celery.
Author-email: Fernando Leon Franco <fernanlee2131@gmail.com>
License: MIT
Classifier: Programming Language :: Python :: 3
Classifier: Framework :: Django
Classifier: License :: OSI Approved :: MIT License
Classifier: Operating System :: OS Independent
Requires-Python: >=3.12.9
License-File: LICENSE
Requires-Dist: Django>=5.0.2
Requires-Dist: djangorestframework>=3.16.0
Requires-Dist: celery[redis]>=5.5.3
Requires-Dist: django-celery-beat>=2.6.0
Requires-Dist: colorstreak>=2.1.3
Requires-Dist: PyJWT>=2.10.1
Requires-Dist: reportlab>=4.4.3
Requires-Dist: qrcode>=8.2
Dynamic: license-file
